{"pageProps":{"frontmatter":{"metaDesc":"Коворкінг у франківському районі Львова, недалеко від ТРЦ Вікторія Гарденс. Безліч різних локацій для роботи, переговорів та відпочинку.","socialImage":"/images/coworkings/lviv/futura-hub/intro.jpg","coworkingName":"Futura Hub","galleryImages":["/images/coworkings/lviv/futura-hub/gallery1.jpg","/images/coworkings/lviv/futura-hub/gallery2.jpg","/images/coworkings/lviv/futura-hub/gallery3.jpg","/images/coworkings/lviv/futura-hub/gallery4.jpg","/images/coworkings/lviv/futura-hub/gallery5.jpg","/images/coworkings/lviv/futura-hub/gallery6.jpg"],"prices":["Закріплене робоче місце в опенспейсі - 190 $ за місяць","Незакріплене робоче місце у лаунж зоні - 120$ за місяць"],"address":"м. Львів, вул. Кульпарківська, 200А","hours":"Пн. - Нд. цілодобово","date":{"publishDate":"2023-01-24T14:37:32.316Z","modifyDate":"2023-01-24T14:37:32.316Z"},"author":{"name":"Sukhrob S.","url":"https://www.facebook.com/alexgreenpol"},"phone":"0800309339","website":"futura-hub.com.ua/category/coworking-uk","faq":[{"question":"Як ви вирішуєте проблеми з перебоями світла?","answer":"Простір оснащений генератором, що забезпечує безперебійне електропостачання для роботи резидентів."},{"question":"У вас є Starlink або як ви вирішуєте проблему з інтернетом?","answer":"Ми підключені до кількох провайдерів на випадок аварійних ситуацій. Наразі проблем з інтернетом немає."},{"question":"У вас є укриття на випадок повітряних тривог?","answer":"У трьох хвилинах ходьби від коворкінгу є укриття на 70 осіб, в якому є інтернет та електрика."}]},"content":"\r\nКоворкінг Futura Hub - це локація для роботи, ідей та мистецтва. Приміщення знаходиться у франківському районі Львова, недалеко від великого ТРЦ Вікторія Гарденс та за 5 хвилин ходьби до найближчої зупинки громадського транспорту. Поруч знаходиться безліч різних кафе та точок швидкого харчування, спорт зали та навіть басейн. Всередині приміщення високі стелі та класний ремонт у стилі хайтек. Багато різних просторів для роботи, переговорів, презентацій та відпочинку. Є ігрова зона з настільними та відеоіграми, дві кухні, душова. Курси англійської мови, які вже включені у оренду.\r\n\r\nДуже сподобалася атмосфера всередині коворкінгу - великий та світлий опенспейс, класні стелі з трубами та вентиляцією, багато зелених рослин та чистота (регулярний клінінг). Загалом є все для повноцінної роботи - зручні меблі, особиста шафка для речей, принтер для друку документів і генератори для безперебійної роботи інтернету та техніки. І дуже важливий момент – доступ до робочого місця дозволено цілодобово та без вихідних.\r\n\r\nЄ можливість орендувати окреме закріплене місце у великому опенспейсі або незакріплене місце в зоні лаунжу, а також, якщо ви одна команда, можна орендувати окремий офіс. За вартістю коворкінг відноситься до розряду вище середнього, всі тарифи та ціни можна побачити трохи нижче.\r\n\r\nЗ переваг я можу виділити:\r\n\r\n-   коворкінг у франківському районі, неподалік ТРЦ Вікторія Гарденс;\r\n-   класна атмосфера та ремонт у стилі хайтек під бетон та дерево, багато зелених рослин;\r\n-   зручні стільці, великі столи, багато простору навколо;\r\n-   наявність генератора та резервної лінії інтернету, на випадок аварій;\r\n-   курси англійської мови, які включені у вартість оренди;\r\n-   цілодобовий доступ без вихідних.\r\n"},"__N_SSG":true}